apafib/__init__.py
apafib/classifiers.py
apafib/config.py
apafib/datasets.py
apafib-0.1.14.dist-info/LICENSE
apafib-0.1.14.dist-info/METADATA
apafib-0.1.14.dist-info/WHEEL
apafib-0.1.14.dist-info/top_level.txt
apafib-0.1.14.dist-info/RECORD
