Metadata-Version: 2.1
Name: apafib
Version: 0.1.14
Summary: Utilities for FIB GEI APA course
Home-page: https://github.com/bejar/apafib
Author: Javier Bejar
Author-email: bejar@cs.upc.edu
Classifier: Programming Language :: Python :: 3
Classifier: License :: OSI Approved :: MIT License
Classifier: Operating System :: OS Independent
Requires-Python: >=3.7
License-File: LICENSE
Requires-Dist: pandas
Requires-Dist: scikit-learn
Requires-Dist: numpy
Requires-Dist: remotezip
Requires-Dist: requests
